intervals.py
python_intervals-1.10.0.dist-info/LICENSE.txt
python_intervals-1.10.0.dist-info/METADATA
python_intervals-1.10.0.dist-info/WHEEL
python_intervals-1.10.0.dist-info/top_level.txt
python_intervals-1.10.0.dist-info/zip-safe
python_intervals-1.10.0.dist-info/RECORD
